cvat_reader
