Metadata-Version: 2.1
Name: cvat-reader
Version: 0.3.1
Summary: Read cvat training set
Home-page: https://github.com/eyedl/cvat_reader
Author: Koen Vossen
Author-email: info@koenvossen.nl
License: BSD
Platform: UNKNOWN
Classifier: Intended Audience :: Developers
Classifier: Intended Audience :: Science/Research
Classifier: Programming Language :: Python :: 3
Classifier: Programming Language :: Python :: 3.6
Classifier: Programming Language :: Python :: 3.7
Classifier: Programming Language :: Python :: 3.8
Classifier: Programming Language :: Python :: 3.9
Classifier: Programming Language :: Python :: 3.10
Classifier: License :: OSI Approved
Classifier: Topic :: Scientific/Engineering
License-File: LICENSE
